Metadata-Version: 1.1
Name: rstwriter
Version: 0.0.8
Summary: A report writer powered with reStructuredText for Pandas library.
Home-page: https://github.com/rafpyprog/rstwriter
Author: Rafael Alves Ribeiro
Author-email: rafael.alves.ribeiro@gmail.com
License: MIT
Download-URL: https://github.com/rafpyprog/rstwriter/tarball/0.0.8
Keywords: reStructuredText,rst,pandas,reporting
Platform: UNKNOWN
